tch/__init__.py
tch/config.py
tch/tch.py
tch-1.0.2.dist-info/METADATA
tch-1.0.2.dist-info/WHEEL
tch-1.0.2.dist-info/entry_points.txt
tch-1.0.2.dist-info/licenses/LICENSE
tch-1.0.2.dist-info/RECORD
