Metadata-Version: 2.4
Name: tch
Version: 1.0.2
Summary: Quick terminal file creation tool
Project-URL: homepage, https://github.com/wyattferguson/tch
Project-URL: repository, https://github.com/wyattferguson/tch.git
Project-URL: documentation, https://github.com/wyattferguson/tch
Project-URL: issues, https://github.com/wyattferguson/tch/issues
Author-email: wyattferguson <wyattf@gmail.com>
License: MIT License
License-File: LICENSE
Keywords: cli,command-line,files,python,touch
Classifier: Development Status :: 5 - Production/Stable
Classifier: Intended Audience :: Developers
Classifier: License :: OSI Approved :: MIT License
Classifier: Natural Language :: English
Classifier: Operating System :: OS Independent
Classifier: Programming Language :: Python
Classifier: Programming Language :: Python :: 3.12
Classifier: Topic :: Utilities
Requires-Python: >=3.12
Requires-Dist: click>=8.1.8
